[
  {
    "ticker": "KXSOLMAXY-27JAN01-170",
    "title": "KXSOLMAXY-27JAN01-170",
    "direction": "NO",
    "contracts": 1,
    "entry_cents": 0,
    "current_cents": 58,
    "dollars_risked": 0,
    "current_value": 0.58,
    "pl_dollars": 0.0,
    "timestamp": ""
  },
  {
    "ticker": "KXSOLMAXY-27JAN01-160",
    "title": "KXSOLMAXY-27JAN01-160",
    "direction": "NO",
    "contracts": 2,
    "entry_cents": 0,
    "current_cents": 72,
    "dollars_risked": 0,
    "current_value": 1.44,
    "pl_dollars": 0.0,
    "timestamp": ""
  },
  {
    "ticker": "KXSOLMAXY-27JAN01-150",
    "title": "KXSOLMAXY-27JAN01-150",
    "direction": "NO",
    "contracts": 2,
    "entry_cents": 0,
    "current_cents": 57,
    "dollars_risked": 0,
    "current_value": 1.14,
    "pl_dollars": 0.0,
    "timestamp": ""
  },
  {
    "ticker": "KXBTCMAXY-26DEC31-149999.99",
    "title": "KXBTCMAXY-26DEC31-149999.99",
    "direction": "NO",
    "contracts": 1,
    "entry_cents": 0,
    "current_cents": 90,
    "dollars_risked": 0,
    "current_value": 0.9,
    "pl_dollars": 0.0,
    "timestamp": ""
  },
  {
    "ticker": "KXTESLASEMI-27JAN-5000",
    "title": "KXTESLASEMI-27JAN-5000",
    "direction": "NO",
    "contracts": 1,
    "entry_cents": 0,
    "current_cents": 84,
    "dollars_risked": 0,
    "current_value": 0.84,
    "pl_dollars": 0.0,
    "timestamp": ""
  }
]